LICENSE
README.md
debug_toolbar/__init__.py
debug_toolbar/api.py
debug_toolbar/middleware.py
debug_toolbar/panels/__init__.py
debug_toolbar/panels/headers.py
debug_toolbar/panels/logging.py
debug_toolbar/panels/profiling.py
debug_toolbar/panels/pydantic.py
debug_toolbar/panels/redirects.py
debug_toolbar/panels/request.py
debug_toolbar/panels/routes.py
debug_toolbar/panels/settings.py
debug_toolbar/panels/sql.py
debug_toolbar/panels/sqlalchemy.py
debug_toolbar/panels/timer.py
debug_toolbar/panels/tortoise.py
debug_toolbar/panels/versions.py
debug_toolbar/py.typed
debug_toolbar/responses.py
debug_toolbar/settings.py
debug_toolbar/statics/css/print.css
debug_toolbar/statics/css/toolbar.css
debug_toolbar/statics/img/icon-green.svg
debug_toolbar/statics/img/icon-white.svg
debug_toolbar/statics/js/redirect.js
debug_toolbar/statics/js/refresh.js
debug_toolbar/statics/js/timer.js
debug_toolbar/statics/js/toolbar.js
debug_toolbar/statics/js/utils.js
debug_toolbar/statics/js/versions.js
debug_toolbar/templates/base.html
debug_toolbar/templates/includes/panel_button.html
debug_toolbar/templates/includes/panel_content.html
debug_toolbar/templates/panels/headers.html
debug_toolbar/templates/panels/logging.html
debug_toolbar/templates/panels/profiling.html
debug_toolbar/templates/panels/pydantic.html
debug_toolbar/templates/panels/request.html
debug_toolbar/templates/panels/routes.html
debug_toolbar/templates/panels/settings.html
debug_toolbar/templates/panels/sql.html
debug_toolbar/templates/panels/timer.html
debug_toolbar/templates/panels/versions.html
debug_toolbar/templates/redirect.html
debug_toolbar/toolbar.py
debug_toolbar/types.py
debug_toolbar/utils.py
fastapi_toolbar-1.0.3.dist-info/LICENSE
fastapi_toolbar-1.0.3.dist-info/WHEEL
fastapi_toolbar-1.0.3.dist-info/METADATA
fastapi_toolbar-1.0.3.dist-info/RECORD
