Metadata-Version: 2.1
Name: fastapi-toolbar
Version: 1.0.3
Summary: A debug toolbar for FastAPI.
Home-page: https://github.com/chrismaille/fastapi-toolbar
License: BSD
Keywords: fastapi,debug,profiling
Author: Dani
Author-email: dani@domake.io
Requires-Python: >=3.8,<4
Classifier: Development Status :: 2 - Pre-Alpha
Classifier: Environment :: Web Environment
Classifier: Framework :: AsyncIO
Classifier: Intended Audience :: Developers
Classifier: Intended Audience :: Information Technology
Classifier: Intended Audience :: System Administrators
Classifier: License :: OSI Approved :: BSD License
Classifier: License :: Other/Proprietary License
Classifier: Operating System :: OS Independent
Classifier: Programming Language :: Python
Classifier: Programming Language :: Python :: 3
Classifier: Programming Language :: Python :: 3.10
Classifier: Programming Language :: Python :: 3.6
Classifier: Programming Language :: Python :: 3.7
Classifier: Programming Language :: Python :: 3.8
Classifier: Programming Language :: Python :: 3.9
Classifier: Topic :: Internet
Classifier: Topic :: Internet :: WWW/HTTP
Classifier: Topic :: Internet :: WWW/HTTP :: HTTP Servers
Classifier: Topic :: Software Development
Classifier: Topic :: Software Development :: Debuggers
Classifier: Topic :: Software Development :: Libraries
Classifier: Topic :: Software Development :: Libraries :: Python Modules
Classifier: Topic :: Utilities
Classifier: Typing :: Typed
Requires-Dist: Jinja2
Requires-Dist: aiofiles
Requires-Dist: anyio
Requires-Dist: fastapi
Requires-Dist: pyinstrument
Requires-Dist: sqlparse
Project-URL: Repository, https://github.com/chrismaille/fastapi-toolbar
